<annotation>
	<folder>train</folder>
	<filename>IMG_0359.jpg</filename>
	<path>/Users/zap/Desktop/snackRec/train/IMG_0359.jpg</path>
	<source>
		<database>Unknown</database>
	</source>
	<size>
		<width>400</width>
		<height>300</height>
		<depth>3</depth>
	</size>
	<segmented>0</segmented>
	<object>
		<name>oreo</name>
		<pose>Unspecified</pose>
		<truncated>0</truncated>
		<difficult>0</difficult>
		<bndbox>
			<xmin>62</xmin>
			<ymin>118</ymin>
			<xmax>314</xmax>
			<ymax>224</ymax>
		</bndbox>
	</object>
</annotation>
